bamnostic/__init__.py
bamnostic/bai.py
bamnostic/bam.py
bamnostic/bgzf.py
bamnostic/core.py
bamnostic/csi.py
bamnostic/utils.py
bamnostic/version
bamnostic/data/example.bam
bamnostic/data/example.bam.bai
bamnostic-1.2.dist-info/licenses/LICENSE
tests/__init__.py
tests/test_build.py
bamnostic-1.2.dist-info/METADATA
bamnostic-1.2.dist-info/WHEEL
bamnostic-1.2.dist-info/top_level.txt
bamnostic-1.2.dist-info/RECORD
